fastui/__init__.py
fastui/__main__.py
fastui/base.py
fastui/class_name.py
fastui/dev.py
fastui/events.py
fastui/forms.py
fastui/generate_typescript.py
fastui/json_schema.py
fastui/py.typed
fastui/types.py
fastui/auth/__init__.py
fastui/auth/github.py
fastui/auth/shared.py
fastui/components/__init__.py
fastui/components/display.py
fastui/components/forms.py
fastui/components/py.typed
fastui/components/tables.py
fastui-0.8.0.dist-info/METADATA
fastui-0.8.0.dist-info/WHEEL
fastui-0.8.0.dist-info/entry_points.txt
fastui-0.8.0.dist-info/licenses/LICENSE
fastui-0.8.0.dist-info/RECORD
