Metadata-Version: 2.4
Name: fastui
Version: 0.8.0
Summary: Build better UIs faster.
Project-URL: Homepage, https://github.com/pydantic/FastUI
Author-email: Samuel Colvin <s@muelcolvin.com>
License-Expression: MIT
License-File: LICENSE
Classifier: Development Status :: 4 - Beta
Classifier: Framework :: FastAPI
Classifier: Framework :: Pydantic :: 2
Classifier: Intended Audience :: Developers
Classifier: Intended Audience :: Information Technology
Classifier: License :: OSI Approved :: MIT License
Classifier: Programming Language :: Python :: 3
Classifier: Programming Language :: Python :: 3 :: Only
Classifier: Programming Language :: Python :: 3.9
Classifier: Programming Language :: Python :: 3.10
Classifier: Programming Language :: Python :: 3.11
Classifier: Programming Language :: Python :: 3.12
Classifier: Programming Language :: Python :: 3.13
Classifier: Topic :: Internet
Requires-Python: >=3.9
Requires-Dist: pydantic[email]>=2.8.0
Provides-Extra: fastapi
Requires-Dist: fastapi>=0.104; extra == 'fastapi'
Requires-Dist: python-multipart>=0.0.6; extra == 'fastapi'
